<?xml version="1.0" encoding="utf-8"?>
<odoo>
    <data>

        <record id="flex_additions_deductions_view_move_form" model="ir.ui.view">
            <field name="name">flex_additions_deductions.account.move.form</field>
            <field name="model">account.move</field>
            <field name="inherit_id" ref="account.view_move_form"/>
            <field name="priority" eval="8"/>
            <field name="arch" type="xml">
                <xpath expr="//field[@name='partner_id']" position="after">
                    <field name="project_invoice_from_sale_order"
                           invisible="there_is_access_from_company_id == False and move_type != 'out_invoice'"/>
                    <field name="deductions_no"
                           invisible="there_is_access_from_company_id == False and move_type != 'out_invoice'"
                           readonly="1"/>
                    <field name="is_out_invoice"
                           invisible="1"
                           readonly="1"/>
                    <field name="project_manager"
                           invisible="there_is_access_from_company_id == False and move_type != 'out_invoice'"
                           readonly="1"/>
                    <field name="projects_manager"
                           invisible="there_is_access_from_company_id == False and move_type != 'out_invoice'"
                           readonly="1"/>
                </xpath>
                <xpath expr="//sheet/div[@name='button_box']" position="inside">
                    <button name="open_created_journal" type="object" class="oe_stat_button"
                            icon="fa-pencil-square-o" invisible="there_is_access_from_company_id == False">
                        <field name="invoice_count" widget="statinfo" string="Deductions/Additions"/>
                    </button>
                </xpath>
                <xpath expr="//field[@name='journal_id']" position="after">
                    <field name="source_Document_for_smart_button" readonly="1"/>
                </xpath>
                <xpath expr="//field[@name='invoice_line_ids']" position="after">
                    <field name="there_is_access_from_company_id" invisible="1"/>

                </xpath>
                <xpath expr="//page[@name='aml_tab']" position="after">
                    <page string="Additions/Deductions" name="flex_additions_deductions_tab"
                          invisible="there_is_access_from_company_id == False">

                        <h2>Deductions</h2>
                        <!--                       there_is_access_from_company_id == False-->
                        <field name="flex_deductions_ids" widget="one2many_list">
                            <tree editable="bottom">
                                <field name="deductions_id" options="{'no_create': True}"/>
                                <field name="name"/>
                                <field name="is_percentage"/>
                                <field name="tax_id"/>
                                <field name="percentage_or_value"/>
                                <field name="amount"/>
                            </tree>
                            <form>
                                <group>
                                    <field name="deductions_id" options="{'no_create': True}"/>
                                    <field name="name"/>
                                    <field name="is_percentage"/>
                                    <field name="tax_id" options="{'no_create': True}"/>
                                    <field name="percentage_or_value"/>
                                    <field name="amount"/>
                                </group>
                            </form>
                        </field>
                        <h2>Additions</h2>
                        <field name="flex_additions_ids" widget="one2many_list">
                            <tree editable="bottom">
                                <field name="additions_id" options="{'no_create': True}"/>
                                <field name="name"/>
                                <field name="is_percentage"/>
                                <field name="tax_id" options="{'no_create': True}"/>
                                <field name="percentage_or_value"/>
                                <field name="amount"/>
                            </tree>
                            <form>
                                <group>
                                    <field name="additions_id"/>
                                    <field name="name"/>
                                    <field name="is_percentage"/>
                                    <field name="tax_id"/>
                                    <field name="percentage_or_value"/>
                                    <field name="amount"/>
                                </group>
                            </form>
                        </field>
                    </page>
                </xpath>
                <xpath expr="//page[@name='invoice_tab']/group[@class='oe_invoice_lines_tab']" position="attributes">
                    <attribute name="invisible">1</attribute>
                </xpath>
                <xpath expr="//page[@name='invoice_tab']/group[@class='oe_invoice_lines_tab']" position="after">
                    <group col="12" class="oe_invoice_lines_tab">
                        <group colspan="8">
                            <field name="narration" placeholder="Terms and Conditions" colspan="2" nolabel="1"/>
                        </group>

                        <group class="oe_subtotal_footer oe_right" colspan="2"
                               name="sale_total">
                            <field name="amount_untaxed" widget='monetary'
                                   options="{'currency_field': 'currency_id'}"/>
                            <field name="deductions_amount_type_discounts" widget='monetary'
                                   options="{'currency_field': 'currency_id'}"
                                   invisible="there_is_access_from_company_id == False"/>
                            <field name="deductions_amount_type_insurances" widget='monetary'
                                   options="{'currency_field': 'currency_id'}"
                                   invisible="there_is_access_from_company_id == False"/>
                            <field name="deductions_amount_type_advance_payment" widget='monetary'
                                   options="{'currency_field': 'currency_id'}"
                                   invisible="there_is_access_from_company_id == False"/>
                            <field name="deductions_amount_type_business_guarantee" widget='monetary'
                                   options="{'currency_field': 'currency_id'}"
                                   invisible="there_is_access_from_company_id == False"/>
                            <field name="deductions_amount" widget='monetary'
                                   options="{'currency_field': 'currency_id'}"
                                   invisible="there_is_access_from_company_id == False"/>
                            <field name="additions_amount" widget='monetary'
                                   options="{'currency_field': 'currency_id'}"
                                   invisible="there_is_access_from_company_id == False"/>
                            <div class="oe_subtotal_footer_separator oe_inline o_td_label">
                                <label for="total_deductions"/>
                            </div>
                            <field name="total_deductions" nolabel="1"
                                   class="oe_subtotal_footer_separator"
                                   widget='monetary'
                                   options="{'currency_field': 'currency_id'}"/>
                            <!--                            <field name="total_deductions" widget='monetary'-->
                            <!--                                   options="{'currency_field': 'currency_id'}"/>-->
                            <field name="amount_tax" widget='monetary'
                                   options="{'currency_field': 'currency_id'}"/>
                            <div class="oe_subtotal_footer_separator oe_inline o_td_label" invisible="1">
                                <label for="amount_total"/>
                            </div>
                            <field name="amount_total" nolabel="1"
                                   class="oe_subtotal_footer_separator"
                                   widget='monetary'
                                   options="{'currency_field': 'currency_id'}" invisible="1"/>

                            <div class="oe_subtotal_footer_separator oe_inline o_td_label"
                                 invisible="there_is_access_from_company_id == False">
                                <label for="all_total_deductions"/>
                            </div>
                            <field name="all_total_deductions" nolabel="1"
                                   class="oe_subtotal_footer_separator"
                                   widget='monetary'
                                   options="{'currency_field': 'currency_id'}"
                                   invisible="there_is_access_from_company_id == False"/>
                        </group>

                        <div class="clearfix"/>
                    </group>
                </xpath>
                <xpath expr="//field[@name='invoice_line_ids']/tree/field[@name='product_id']" position="before">
                    <field name="line_number" column_invisible="1"/>

                </xpath>
                <xpath expr="//field[@name='invoice_line_ids']/tree/field[@name='price_unit']" position="before">
                    <!--                    <field name="move_id" column_invisible="1"/>-->
                    <!--                    <field name="is_out_invoice" column_invisible="1"/>-->
                    <field name="current_accomplishment"
                           column_invisible="parent.is_out_invoice == False and parent.there_is_access_from_company_id == False"/>
                    <field name="previous_accomplishment"
                           column_invisible="parent.is_out_invoice == False and parent.there_is_access_from_company_id == False"/>
                    <field name="total_accomplishment"
                           column_invisible="parent.is_out_invoice == False and parent.there_is_access_from_company_id == False"/>
                </xpath>
            </field>
        </record>
    </data>
</odoo>